a_sync/__init__.py
a_sync/a_sync.py
a_sync/examples.py
a_sync/helpers.py
a_sync-0.5.0.dist-info/DESCRIPTION.rst
a_sync-0.5.0.dist-info/METADATA
a_sync-0.5.0.dist-info/RECORD
a_sync-0.5.0.dist-info/WHEEL
a_sync-0.5.0.dist-info/metadata.json
a_sync-0.5.0.dist-info/top_level.txt
